tree_sitter_yaml/__init__.py
tree_sitter_yaml/__init__.pyi
tree_sitter_yaml/_binding.abi3.so
tree_sitter_yaml/binding.c
tree_sitter_yaml/py.typed
tree_sitter_yaml/queries/highlights.scm
tree_sitter_yaml-0.7.1.dist-info/METADATA
tree_sitter_yaml-0.7.1.dist-info/WHEEL
tree_sitter_yaml-0.7.1.dist-info/top_level.txt
tree_sitter_yaml-0.7.1.dist-info/RECORD
tree_sitter_yaml-0.7.1.dist-info/licenses/LICENSE
