Metadata-Version: 2.4
Name: tree-sitter-yaml
Version: 0.7.1
Summary: YAML grammar for tree-sitter
Author-email: Ika <ikatyang@gmail.com>, Amaan Qureshi <amaanq12@gmail.com>
License: MIT
Project-URL: Homepage, https://github.com/tree-sitter-grammars/tree-sitter-yaml
Keywords: incremental,parsing,tree-sitter,yaml
Classifier: Intended Audience :: Developers
Classifier: Topic :: Software Development :: Compilers
Classifier: Topic :: Text Processing :: Linguistic
Classifier: Typing :: Typed
Requires-Python: >=3.10
License-File: LICENSE
Provides-Extra: core
Requires-Dist: tree-sitter~=0.24; extra == "core"
Dynamic: license-file
